pbp/__init__.py
pbp/cloud/__init__.py
pbp/cloud/main_cloud.py
pbp/file_helper.py
pbp/hmb_gen/__init__.py
pbp/hmb_gen/file_helper.py
pbp/hmb_gen/hmb_metadata.py
pbp/hmb_gen/hmso_pypam.py
pbp/hmb_gen/json_support.py
pbp/hmb_gen/main_hmb_generator.py
pbp/hmb_gen/main_hmb_generator_args.py
pbp/hmb_gen/main_hmb_generator_file.py
pbp/hmb_gen/misc_helper.py
pbp/hmb_gen/process_helper.py
pbp/hmb_gen/pypam_support.py
pbp/hmb_gen/simpleapi.py
pbp/hmb_metadata.py
pbp/hmb_plot/__init__.py
pbp/hmb_plot/main_plot.py
pbp/hmb_plot/plot_const.py
pbp/hmb_plot/plotting.py
pbp/logging_helper.py
pbp/main_cli.py
pbp/meta_gen/__init__.py
pbp/meta_gen/gen_abstract.py
pbp/meta_gen/gen_iclisten.py
pbp/meta_gen/gen_nrs.py
pbp/meta_gen/gen_resea.py
pbp/meta_gen/gen_soundtrap.py
pbp/meta_gen/json_generator.py
pbp/meta_gen/main_meta_generator.py
pbp/meta_gen/main_meta_generator_args.py
pbp/meta_gen/meta_reader.py
pbp/meta_gen/utils.py
pbp/misc_helper.py
pbp/plotting.py
pbp/process_helper.py
pbp/pypam_support.py
pbp/simpleapi.py
pbp/util/__init__.py
pbp/util/bucket_key_simple.py
pbp/util/datetime_helper.py
pbp/util/logging_helper.py
pbp/util/uri_handler.py
mbari_pbp-1.8.72.dist-info/METADATA
mbari_pbp-1.8.72.dist-info/WHEEL
mbari_pbp-1.8.72.dist-info/entry_points.txt
mbari_pbp-1.8.72.dist-info/licenses/LICENSE
mbari_pbp-1.8.72.dist-info/RECORD
