Metadata-Version: 2.4
Name: mbari-pbp
Version: 1.8.72
Summary: PyPAM based Processing
License: Apache-2.0
License-File: LICENSE
Author: Carlos Rueda
Author-email: carueda@mbari.org
Maintainer: Carlos Rueda
Maintainer-email: carueda@mbari.org
Requires-Python: >=3.9,<3.12.0
Classifier: License :: OSI Approved :: Apache Software License
Classifier: Programming Language :: Python :: 3
Classifier: Programming Language :: Python :: 3.9
Classifier: Programming Language :: Python :: 3.10
Classifier: Programming Language :: Python :: 3.11
Requires-Dist: Pyarrow (==15.0.0)
Requires-Dist: awscli (>=1.33.20,<2.0.0)
Requires-Dist: boto3 (==1.34.47)
Requires-Dist: dataclasses-json (==0.6)
Requires-Dist: google-cloud-storage (==2.18.0)
Requires-Dist: h5netcdf (==1.3.0)
Requires-Dist: isodate (>=0.7.2,<0.8.0)
Requires-Dist: lifewatch-pypam (==0.3.2)
Requires-Dist: loguru[mypy] (>=0.7.2,<0.8.0)
Requires-Dist: marshmallow (==3.20.2)
Requires-Dist: progressbar2 (==3.53.1)
Requires-Dist: pvlib (>=0.11.0,<0.12.0)
Requires-Dist: python-dateutil (==2.8.2)
Requires-Dist: pyyaml (==6.0)
Requires-Dist: soundfile (==0.12.1)
Project-URL: Homepage, https://docs.mbari.org/pbp/
Project-URL: Repository, https://github.com/mbari-org/pbp
